{"ygPerms":{"resourceCapabilityList":[{"resourceType":"GROUP","capabilities":[{"name":"READ"},{"name":"JOIN"}]},{"resourceType":"PHOTO","capabilities":[]},{"resourceType":"FILE","capabilities":[]},{"resourceType":"MEMBER","capabilities":[]},{"resourceType":"LINK","capabilities":[]},{"resourceType":"CALENDAR","capabilities":[]},{"resourceType":"DATABASE","capabilities":[]},{"resourceType":"POLL","capabilities":[]},{"resourceType":"MESSAGE","capabilities":[{"name":"READ"}]},{"resourceType":"PENDING_MESSAGE","capabilities":[]},{"resourceType":"ATTACHMENTS","capabilities":[{"name":"READ"}]},{"resourceType":"PHOTOMATIC_ALBUMS","capabilities":[]},{"resourceType":"MEMBERSHIP_TYPE","capabilities":[]},{"resourceType":"POST","capabilities":[{"name":"READ"}]},{"resourceType":"PIN","capabilities":[]}],"groupUrl":"groups.yahoo.com","intlCode":"us"},"comscore":"pageview_candidate","ygData":{"userId":254563161,"authorName":"Dan Smyth","from":"&quot;Dan Smyth&quot; &lt;das69@...&gt;","profile":"dan_gaidin_ut","replyTo":"LIST","senderId":"LlOOkvtPgoCRnThT_l1PmubIDiJPFZu_9_HOCW4lImQFfVNX8NeDB3Eml6_6qfuBtfqttBuozvIfszPsRJqq0Sdn7EYL","spamInfo":{"isSpam":false,"reason":"6"},"subject":"Re: Installing cantera...","postDate":"1149795182","msgId":1245,"canDelete":false,"contentTrasformed":false,"systemMessage":false,"headers":{"messageIdInHeader":"PGU2OXUxZStwYTdnQGVHcm91cHMuY29tPg==","inReplyToHeader":"PDAzRDgzQzkxLTZBQUMtNDFERS1CNUY5LURGMzRDOUFGRjdBREBjYWx0ZWNoLmVkdT4="},"prevInTopic":1244,"nextInTopic":0,"prevInTime":1244,"nextInTime":1246,"topicId":1240,"numMessagesInTopic":5,"msgSnippet":"I ve been trying to get either version to run make and work.  Right now, with cantera-1.6.0r2 I m getting a bundle of mess that starts with this: cd","rawEmail":"Return-Path: &lt;das69@...&gt;\r\nX-Sender: das69@...\r\nX-Apparently-To: cantera@yahoogroups.com\r\nReceived: (qmail 27353 invoked from network); 8 Jun 2006 19:35:10 -0000\r\nReceived: from unknown (66.218.67.34)\n  by m34.grp.scd.yahoo.com with QMQP; 8 Jun 2006 19:35:10 -0000\r\nReceived: from unknown (HELO n8a.bullet.sc5.yahoo.com) (66.163.187.151)\n  by mta8.grp.scd.yahoo.com with SMTP; 8 Jun 2006 19:35:10 -0000\r\nReceived: from [66.163.187.123] by n8.bullet.sc5.yahoo.com with NNFMP; 08 Jun 2006 19:33:02 -0000\r\nReceived: from [66.218.69.1] by t4.bullet.sc5.yahoo.com with NNFMP; 08 Jun 2006 19:33:02 -0000\r\nReceived: from [66.218.66.76] by t1.bullet.scd.yahoo.com with NNFMP; 08 Jun 2006 19:33:02 -0000\r\nDate: Thu, 08 Jun 2006 19:33:02 -0000\r\nTo: cantera@yahoogroups.com\r\nMessage-ID: &lt;e69u1e+pa7g@...&gt;\r\nIn-Reply-To: &lt;03D83C91-6AAC-41DE-B5F9-DF34C9AFF7AD@...&gt;\r\nUser-Agent: eGroups-EW/0.82\r\nMIME-Version: 1.0\r\nContent-Type: text/plain; charset=&quot;ISO-8859-1&quot;\r\nContent-Transfer-Encoding: quoted-printable\r\nX-Mailer: Yahoo Groups Message Poster\r\nX-Yahoo-Newman-Property: groups-compose\r\nX-eGroups-Msg-Info: 1:6:0:0\r\nFrom: &quot;Dan Smyth&quot; &lt;das69@...&gt;\r\nSubject: Re: Installing cantera...\r\nX-Yahoo-Group-Post: member; u=254563161; y=KfqTxxEdOD9KDrcemYu0Ss1MUu5q5aFRs0zdMZSybI-w7J5KQ3D3Eg\r\nX-Yahoo-Profile: dan_gaidin_ut\r\n\r\nI&#39;ve been trying to get either version to run &quot;make&quot; and work.  Right\nnow, =\r\nwith cantera-1.6.0r2 I&#39;m getting a bundle of mess that starts\nwith this:\n\nc=\r\nd Cantera/cxx/src; make\nmake[1]: Entering directory\n`/auto/grp4/HMX_propell=\r\nants/cantera-1.6.0r2/Cantera/cxx/src&#39;\ng++ -c cxxutils.cpp -I../../src   -O3=\r\n -Wall\nIn file included from State.h:22,\n                 from Phase.h:16,\n=\r\n                 from ThermoPhase.h:20,\n                 from cxxutils.cpp:=\r\n7:\nct_defs.h:52: error: `doublereal&#39; does not name a type\n\nThe same error i=\r\ns coming up in multiple header and cpp files listed\nafterwards.  \n\nBy the w=\r\nay, is this the right place to be asking questions like this?\n Just want to=\r\n make sure I&#39;m not wasting anyone&#39;s time.  Thanks.\n\nDan\n\n\n--- In cantera@ya=\r\nhoogroups.com, David Goodwin &lt;dgoodwin@...&gt; wrote:\n&gt;\n&gt; Dan,\n&gt; \n&gt; I too am f=\r\ninding a problem building on linux, but it is a little  \n&gt; different than t=\r\nhe problem you describe. However, it occurs at the  \n&gt; same point - trying =\r\nto link demos.cpp.\n&gt; \n&gt; On my machine:\n&gt; uname -m=3Di686\n&gt; uname -r=3D2.6.1=\r\n1-1.1369_FC4\n&gt; uname-s=3DLinux\n&gt; \n&gt; I checked out a fresh working copy of C=\r\nantera, and edited the  \n&gt; &#39;preconfig&#39; script only to turn off using sundia=\r\nls. I then ran:\n&gt; \n&gt; ./predef\n&gt; make\n&gt; \n&gt; For me, the problem is that the s=\r\nystem does not seem to be able to  \n&gt; find the &quot;stdc++&quot; libraries.  If I sp=\r\necify the library as &quot;-lstdc++&quot;  \n&gt; the build fails, and the functions it s=\r\nays it can&#39;t find are ones in  \n&gt; this library.  If I explicitly add file &quot;=\r\n/usr/lib/libstdc++.so.6&quot; to  \n&gt; the build command line, then the build of t=\r\nhe demo program succeeds.\n&gt; \n&gt; I don&#39;t think this is a Cantera error, since=\r\n I believe specifying &quot;- \n&gt; lstdc++&quot; should cause the linker to look for bo=\r\nth static (.a) and  \n&gt; dynamic (.so) libraries.  But I don&#39;t know what caus=\r\nes it.  I will  \n&gt; explore a bit more.\n&gt; \n&gt; I don&#39;t know if this error has =\r\nthe same cause as the one you are  \n&gt; getting.  I would recommend checking =\r\nout a fresh version (rather than  \n&gt; updating from CVS) and trying to build=\r\n.\n&gt; \n&gt; Any linux gurus out there know what is going on here?\n&gt; \n&gt; (For what=\r\n it is worth, this problem seems to be specific to linux; I  \n&gt; don&#39;t encou=\r\nnter any problem building Cantera on Mac OSX, either on  \n&gt; Intel or PPC ma=\r\nchines.)\n&gt; \n&gt; Dave\n&gt; \n&gt; \n&gt; \n&gt; \n&gt; On Jun 7, 2006, at 4:44 PM, Dan Smyth wrot=\r\ne:\n&gt; \n&gt; &gt; I&#39;m tyring to install cantera on a Linux machine:\n&gt; &gt; uname -m =\r\n=3D i686\n&gt; &gt; uname -r =3D 2.6.9-22.ELsmp\n&gt; &gt; uname -s =3D Linux\n&gt; &gt; I updat=\r\ned from CVS today and got the following errors after copying\n&gt; &gt; loads of *=\r\n.h files to where they needed to go and adding some &quot;ar ruv&quot;\n&gt; &gt; and &quot;ranli=\r\nb&quot; commands to where they used to be in the Makefile of\n&gt; &gt; Cantera-1.6.\n&gt; =\r\n&gt;\n&gt; &gt; make[2]: Entering directory\n&gt; &gt; `/auto/grp4/HMX_propellants/cantera/C=\r\nantera/cxx/demos&#39;\n&gt; &gt; g++ -c demos.cpp\n&gt; &gt; -I/fsh/das69/groups/HMX_propella=\r\nnts/cantera/build/include -g -O2\n&gt; &gt; In file included from rankine.cpp:7,\n&gt;=\r\n &gt;                  from demos.cpp:7:\n&gt; &gt; /fsh/das69/groups/HMX_propellants=\r\n/cantera/build/include/cantera/ \n&gt; &gt; PureFluid.h:15:\n&gt; &gt; error: expected cl=\r\nass-name before &#39;{&#39; token\n&gt; &gt; /fsh/das69/groups/HMX_propellants/cantera/bui=\r\nld/include/cantera/ \n&gt; &gt; PureFluid.h:\n&gt; &gt; In constructor `Cantera::PureFlui=\r\nd::PureFluid(std::string,  \n&gt; &gt; std::string)&#39;:\n&gt; &gt; /fsh/das69/groups/HMX_pr=\r\nopellants/cantera/build/include/cantera/ \n&gt; &gt; PureFluid.h:24:\n&gt; &gt; error: ca=\r\nnnot convert `Cantera::PureFluid* const&#39; to\n&gt; &gt; `Cantera::ThermoPhase*&#39; for=\r\n argument `4&#39; to `bool\n&gt; &gt; Cantera::buildSolutionFromXML(Cantera::XML_Node&=\r\n, std::string,\n&gt; &gt; std::string, Cantera::ThermoPhase*, Cantera::Kinetics*)&#39;=\r\n\n&gt; &gt; /fsh/das69/groups/HMX_propellants/cantera/build/include/cantera/ \n&gt; &gt; =\r\nPureFluid.h:\n&gt; &gt; In constructor `Cantera::PureFluid::PureFluid(Cantera::XML=\r\n_Node&,\n&gt; &gt; std::string)&#39;:\n&gt; &gt; /fsh/das69/groups/HMX_propellants/cantera/bu=\r\nild/include/cantera/ \n&gt; &gt; PureFluid.h:31:\n&gt; &gt; error: cannot convert `Canter=\r\na::PureFluid* const&#39; to\n&gt; &gt; `Cantera::ThermoPhase*&#39; for argument `4&#39; to `bo=\r\nol\n&gt; &gt; Cantera::buildSolutionFromXML(Cantera::XML_Node&, std::string,\n&gt; &gt; s=\r\ntd::string, Cantera::ThermoPhase*, Cantera::Kinetics*)&#39;\n&gt; &gt; /fsh/das69/grou=\r\nps/HMX_propellants/cantera/build/include/cantera/ \n&gt; &gt; PureFluid.h:\n&gt; &gt; In =\r\nfunction `std::ostream& Cantera::operator&lt;&lt;(std::ostream&,\n&gt; &gt; Cantera::Pur=\r\neFluid&)&#39;:\n&gt; &gt; /fsh/das69/groups/HMX_propellants/cantera/build/include/cant=\r\nera/ \n&gt; &gt; PureFluid.h:39:\n&gt; &gt; error: invalid initialization of reference of=\r\n type &#39;const\n&gt; &gt; Cantera::ThermoPhase&&#39; from expression of type &#39;Cantera::P=\r\nureFluid&#39;\n&gt; &gt; /fsh/das69/groups/HMX_propellants/cantera/build/include/cante=\r\nra/ \n&gt; &gt; kernel/stringUtils.h:28:\n&gt; &gt; error: in passing argument 1 of `std:=\r\n:string Cantera::report(const\n&gt; &gt; Cantera::ThermoPhase&, bool)&#39;\n&gt; &gt; In file=\r\n included from demos.cpp:7:\n&gt; &gt; rankine.cpp: In function `int openRankine(i=\r\nnt, void*)&#39;:\n&gt; &gt; rankine.cpp:48: error: &#39;class Cantera::Water&#39; has no membe=\r\nr named\n&gt; &gt; &#39;setState_TP&#39;\n&gt; &gt; rankine.cpp:52: error: &#39;class Cantera::Water&#39;=\r\n has no member named\n&gt; &gt; &#39;setState_SP&#39;\n&gt; &gt; rankine.cpp:55: error: &#39;class Ca=\r\nntera::Water&#39; has no member named\n&gt; &gt; &#39;setState_HP&#39;\n&gt; &gt; rankine.cpp:59: err=\r\nor: &#39;class Cantera::Water&#39; has no member named\n&gt; &gt; &#39;setState_Psat&#39;\n&gt; &gt; rank=\r\nine.cpp:63: error: &#39;class Cantera::Water&#39; has no member named\n&gt; &gt; &#39;setState=\r\n_SP&#39;\n&gt; &gt; rankine.cpp:67: error: &#39;class Cantera::Water&#39; has no member named\n=\r\n&gt; &gt; &#39;setState_HP&#39;\n&gt; &gt; rankine.cpp: In function `void saveState(F&, std::str=\r\ning) [with F =3D\n&gt; &gt; Cantera::Water]&#39;:\n&gt; &gt; rankine.cpp:49:   instantiated f=\r\nrom here\n&gt; &gt; rankine.cpp:20: error: &#39;class Cantera::Water&#39; has no member na=\r\nmed\n&gt; &gt; &#39;enthalpy_mass&#39;\n&gt; &gt; rankine.cpp:21: error: &#39;class Cantera::Water&#39; h=\r\nas no member named\n&gt; &gt; &#39;entropy_mass&#39;\n&gt; &gt; rankine.cpp:22: error: &#39;class Can=\r\ntera::Water&#39; has no member named\n&gt; &gt; &#39;temperature&#39;\n&gt; &gt; rankine.cpp:23: erro=\r\nr: &#39;class Cantera::Water&#39; has no member named\n&gt; &gt; &#39;pressure&#39;\n&gt; &gt; rankine.cp=\r\np:24: error: &#39;class Cantera::Water&#39; has no member named\n&gt; &gt; &#39;vaporFraction&#39;=\r\n\n&gt; &gt; make[2]: *** [demos.o] Error 1\n&gt; &gt; make[2]: Leaving directory\n&gt; &gt; `/au=\r\nto/grp4/HMX_propellants/cantera/Cantera/cxx/demos&#39;\n&gt; &gt; make[1]: *** [all] E=\r\nrror 2\n&gt; &gt; make[1]: Leaving directory\n&gt; &gt; `/auto/grp4/HMX_propellants/cante=\r\nra/Cantera/cxx&#39;\n&gt; &gt; make: *** [cxxlib] Error 2\n&gt; &gt;\n&gt; &gt; I&#39;m just having a bo=\r\noger of time figuring this out.  Any help would be\n&gt; &gt; most appreciated.  T=\r\nhanks.\n&gt; &gt;\n&gt; &gt; Dan Smyth\n&gt; &gt;\n&gt; &gt;\n&gt; &gt;\n&gt; &gt;\n&gt; &gt;\n&gt; &gt;\n&gt; &gt;\n&gt; &gt;\n&gt; &gt; --------------=\r\n---------- Yahoo! Groups Sponsor -------------------- \n&gt; &gt; ~--&gt;\n&gt; &gt; Home is=\r\n just a click away.  Make Yahoo! your home page now.\n&gt; &gt; http://us.click.ya=\r\nhoo.com/DHchtC/3FxNAA/yQLSAA/UGYolB/TM\n&gt; &gt; --------------------------------=\r\n------------------------------------ \n&gt; &gt; ~-&gt;\n&gt; &gt;\n&gt; &gt;\n&gt; &gt; Yahoo! Groups Lin=\r\nks\n&gt; &gt;\n&gt; &gt;\n&gt; &gt;\n&gt; &gt;\n&gt; &gt;\n&gt; &gt;\n&gt; &gt;\n&gt;\n\n\n\n\n\n\n"}}