{"ygPerms":{"resourceCapabilityList":[{"resourceType":"GROUP","capabilities":[{"name":"READ"},{"name":"JOIN"}]},{"resourceType":"PHOTO","capabilities":[]},{"resourceType":"FILE","capabilities":[]},{"resourceType":"MEMBER","capabilities":[]},{"resourceType":"LINK","capabilities":[]},{"resourceType":"CALENDAR","capabilities":[]},{"resourceType":"DATABASE","capabilities":[]},{"resourceType":"POLL","capabilities":[]},{"resourceType":"MESSAGE","capabilities":[{"name":"READ"}]},{"resourceType":"PENDING_MESSAGE","capabilities":[]},{"resourceType":"ATTACHMENTS","capabilities":[{"name":"READ"}]},{"resourceType":"PHOTOMATIC_ALBUMS","capabilities":[]},{"resourceType":"MEMBERSHIP_TYPE","capabilities":[]},{"resourceType":"POST","capabilities":[{"name":"READ"}]},{"resourceType":"PIN","capabilities":[]}],"groupUrl":"groups.yahoo.com","intlCode":"us"},"comscore":"pageview_candidate","ygData":{"userId":157334857,"authorName":"kevinmwalters","from":"&quot;kevinmwalters&quot; &lt;kwalters@...&gt;","profile":"kevinmwalters","replyTo":"LIST","senderId":"6a9iDpzEc0FeyFoPCsXeezLEFmw8nURplMsRqR6jM1y0LlGWZQqCO4tXmvAByIUIDdKEDCgVKgnWzvi0Gh8hY38CVcmBjl2IftY668D9","spamInfo":{"isSpam":false,"reason":"6"},"subject":"Some strange errors from cti files...","postDate":"1175741488","msgId":1572,"canDelete":false,"contentTrasformed":false,"systemMessage":false,"headers":{"messageIdInHeader":"PGV2MW83ZytwMXI5QGVHcm91cHMuY29tPg=="},"prevInTopic":0,"nextInTopic":1573,"prevInTime":1571,"nextInTime":1573,"topicId":1572,"numMessagesInTopic":2,"msgSnippet":"I get a duplicate reaction error for the following reactions: ************************************************ Cantera Error! ","rawEmail":"Return-Path: &lt;kwalters@...&gt;\r\nX-Sender: kwalters@...\r\nX-Apparently-To: cantera@yahoogroups.com\r\nReceived: (qmail 35881 invoked from network); 5 Apr 2007 02:51:29 -0000\r\nReceived: from unknown (66.218.66.72)\n  by m31.grp.scd.yahoo.com with QMQP; 5 Apr 2007 02:51:29 -0000\r\nReceived: from unknown (HELO n10c.bullet.sp1.yahoo.com) (69.147.64.105)\n  by mta14.grp.scd.yahoo.com with SMTP; 5 Apr 2007 02:51:29 -0000\r\nReceived: from [216.252.122.218] by n10.bullet.sp1.yahoo.com with NNFMP; 05 Apr 2007 02:51:29 -0000\r\nReceived: from [66.218.69.3] by t3.bullet.sp1.yahoo.com with NNFMP; 05 Apr 2007 02:51:29 -0000\r\nReceived: from [66.218.66.80] by t3.bullet.scd.yahoo.com with NNFMP; 05 Apr 2007 02:51:29 -0000\r\nDate: Thu, 05 Apr 2007 02:51:28 -0000\r\nTo: cantera@yahoogroups.com\r\nMessage-ID: &lt;ev1o7g+p1r9@...&gt;\r\nUser-Agent: eGroups-EW/0.82\r\nMIME-Version: 1.0\r\nContent-Type: text/plain; charset=&quot;ISO-8859-1&quot;\r\nContent-Transfer-Encoding: quoted-printable\r\nX-Mailer: Yahoo Groups Message Poster\r\nX-Yahoo-Newman-Property: groups-compose\r\nX-eGroups-Msg-Info: 1:6:0:0\r\nFrom: &quot;kevinmwalters&quot; &lt;kwalters@...&gt;\r\nSubject: Some strange errors from cti files...\r\nX-Yahoo-Group-Post: member; u=157334857; y=1kO8nHJ7lbcpvH3GBapMEPROUkgZFn31K9LYhsaB8rclDkmtlzhAIg\r\nX-Yahoo-Profile: kevinmwalters\r\n\r\nI get a duplicate reaction error for the following reactions:\n\n************=\r\n************************************\n                Cantera Error!        =\r\n          \n************************************************\nProcedure: inst=\r\nallReaction\nError:   Undeclared duplicate reactions detected: \nReaction 40:=\r\n CH3OO. + CC(*O)OO. &lt;=3D&gt; CH3O. + O2 + CO2 + CH3\nReaction 639: CH3 + O2 &lt;=\r\n=3D&gt; CH3OO.\n\n\nShould these just be listed as DUPLICATE, or is this a bug in=\r\n ck2cti /\ncti interpreter?\n_____________________________________\n\nI also ge=\r\nt this error:\n\n\n\n************************************************\n         =\r\n       Cantera Error!                  \n***********************************=\r\n*************\n\n\nProcedure: getRateCoefficient\nError:   negative or zero A c=\r\noefficient for reaction 1983\n\n\n\n#  Reaction 1983\n# 95HIP/NEU               =\r\n                                              \nreaction(  &quot;H2O2 + OH &lt;=3D&gt; =\r\nHO2 + H2O&quot;,  [2.67000E+41, -7, 37600],\n         options =3D [&quot;duplicate&quot;])\n=\r\n\nAny idea what the cause of this may be? The A factor for this is\nlisted as=\r\n 2.67E41, which is neither 0 nor negative...\n\n\n\n\n\n"}}