{"ygPerms":{"resourceCapabilityList":[{"resourceType":"GROUP","capabilities":[{"name":"READ"},{"name":"JOIN"}]},{"resourceType":"PHOTO","capabilities":[]},{"resourceType":"FILE","capabilities":[]},{"resourceType":"MEMBER","capabilities":[]},{"resourceType":"LINK","capabilities":[]},{"resourceType":"CALENDAR","capabilities":[]},{"resourceType":"DATABASE","capabilities":[]},{"resourceType":"POLL","capabilities":[]},{"resourceType":"MESSAGE","capabilities":[{"name":"READ"}]},{"resourceType":"PENDING_MESSAGE","capabilities":[]},{"resourceType":"ATTACHMENTS","capabilities":[{"name":"READ"}]},{"resourceType":"PHOTOMATIC_ALBUMS","capabilities":[]},{"resourceType":"MEMBERSHIP_TYPE","capabilities":[]},{"resourceType":"POST","capabilities":[{"name":"READ"}]},{"resourceType":"PIN","capabilities":[]}],"groupUrl":"groups.yahoo.com","intlCode":"us"},"comscore":"pageview_candidate","ygData":{"userId":44728387,"authorName":"David Goodwin","from":"David Goodwin &lt;dgoodwin@...&gt;","profile":"dggoodwin","replyTo":"LIST","senderId":"3ksf7tO8x573gz_IanTxfSZXfml1zsF_v8J_nLbaw4z6-6iCTdypdVXQobnc-k3MgeIcnpLM2LRJ0NXVWq16tK7UYyO7CkvKJi0o","spamInfo":{"isSpam":false,"reason":"0"},"subject":"Re: [cantera] Hi","postDate":"1090670120","msgId":447,"canDelete":false,"contentTrasformed":false,"systemMessage":false,"headers":{"messageIdInHeader":"PDU2OEVDOTA4LURENjgtMTFEOC04NDQzLTAwMEQ5M0FFMjQxQUBjYWx0ZWNoLmVkdT4=","inReplyToHeader":"PGNkbGpwaStvdG1vQGVHcm91cHMuY29tPg==","referencesHeader":"PGNkbGpwaStvdG1vQGVHcm91cHMuY29tPg=="},"prevInTopic":445,"nextInTopic":0,"prevInTime":446,"nextInTime":448,"topicId":445,"numMessagesInTopic":2,"msgSnippet":"MATLAB is not finding GRI30.m, which probably means you haven t added the Cantera toolbox to the MATLAB path.  See file ctpath.m in directory cantera within","rawEmail":"Return-Path: &lt;dgoodwin@...&gt;\r\nX-Sender: dgoodwin@...\r\nX-Apparently-To: cantera@yahoogroups.com\r\nReceived: (qmail 35131 invoked from network); 24 Jul 2004 11:55:24 -0000\r\nReceived: from unknown (66.218.66.172)\n  by m10.grp.scd.yahoo.com with QMQP; 24 Jul 2004 11:55:24 -0000\r\nReceived: from unknown (HELO outgoing-mail.its.caltech.edu) (131.215.49.69)\n  by mta4.grp.scd.yahoo.com with SMTP; 24 Jul 2004 11:55:24 -0000\r\nReceived: from earth-dog (earth-dog [192.168.1.3])\n\tby water-ox-postvirus (Postfix) with ESMTP id 3429E26AC10\n\tfor &lt;cantera@yahoogroups.com&gt;; Sat, 24 Jul 2004 04:55:24 -0700 (PDT)\r\nReceived: from water-ox ([192.168.1.10])\n\tby earth-dog (MailMonitor for SMTP v1.2.2 ) ;\n\tSat, 24 Jul 2004 04:55:23 -0700 (PDT)\r\nReceived: from [192.168.1.100] (charter-241-017.caltech.edu [131.215.241.17])\n\tby water-ox.its.caltech.edu (Postfix) with ESMTP id 584BD26AC10\n\tfor &lt;cantera@yahoogroups.com&gt;; Sat, 24 Jul 2004 04:55:23 -0700 (PDT)\r\nMime-Version: 1.0 (Apple Message framework v618)\r\nIn-Reply-To: &lt;cdljpi+otmo@...&gt;\r\nReferences: &lt;cdljpi+otmo@...&gt;\r\nContent-Type: text/plain; charset=US-ASCII; format=flowed\r\nMessage-Id: &lt;568EC908-DD68-11D8-8443-000D93AE241A@...&gt;\r\nContent-Transfer-Encoding: 7bit\r\nDate: Sat, 24 Jul 2004 04:55:20 -0700\r\nTo: cantera@yahoogroups.com\r\nX-Mailer: Apple Mail (2.618)\r\nX-Spam-Status: No, hits=0.0 tagged_above=-100000.0 required=5.0 \r\nX-Spam-Level: \r\nX-eGroups-Remote-IP: 131.215.49.69\r\nFrom: David Goodwin &lt;dgoodwin@...&gt;\r\nSubject: Re: [cantera] Hi\r\nX-Yahoo-Group-Post: member; u=44728387\r\nX-Yahoo-Profile: dggoodwin\r\n\r\nMATLAB is not finding GRI30.m, which probably means you haven&#39;t added \nthe Cantera toolbox to the MATLAB path.  See file ctpath.m in directory \n&#39;cantera&#39; within the installation directory for an m-file that will do \nthis.\n\nOn Jul 21, 2004, at 4:24 AM, prasat_kumar wrote:\n\n&gt; I have downloaded cantera 1.5.4 package in Red hat linux 9.\n&gt; but I have no numerics package installed in linux for python.\n&gt; so in the configure file I just said minimal option in python.\n&gt; then I tried to insall matlab cantera package.\n&gt; configure\n&gt; make make install\n&gt; also source the setup_cantera in my .cshrc file\n&gt; But now I started run the tutrials case I get the follwing error in\n&gt; tutorial 1\n&gt; GRI30 not found.\n&gt;\n&gt; Please help what is the problem.\n&gt; Prasat\n&gt;\n&gt;\n&gt;\n&gt;\n&gt;\n&gt;\n&gt;\n&gt; Yahoo! Groups Links\n&gt;\n&gt;\n&gt;\n&gt;\n&gt;\n&gt;\n\n\n\n"}}