{"ygPerms":{"resourceCapabilityList":[{"resourceType":"GROUP","capabilities":[{"name":"READ"},{"name":"JOIN"}]},{"resourceType":"PHOTO","capabilities":[]},{"resourceType":"FILE","capabilities":[]},{"resourceType":"MEMBER","capabilities":[]},{"resourceType":"LINK","capabilities":[]},{"resourceType":"CALENDAR","capabilities":[]},{"resourceType":"DATABASE","capabilities":[]},{"resourceType":"POLL","capabilities":[]},{"resourceType":"MESSAGE","capabilities":[{"name":"READ"}]},{"resourceType":"PENDING_MESSAGE","capabilities":[]},{"resourceType":"ATTACHMENTS","capabilities":[{"name":"READ"}]},{"resourceType":"PHOTOMATIC_ALBUMS","capabilities":[]},{"resourceType":"MEMBERSHIP_TYPE","capabilities":[]},{"resourceType":"POST","capabilities":[{"name":"READ"}]},{"resourceType":"PIN","capabilities":[]}],"groupUrl":"groups.yahoo.com","intlCode":"us"},"comscore":"pageview_candidate","ygData":{"userId":44728387,"authorName":"David Goodwin","from":"David Goodwin &lt;dgoodwin@...&gt;","profile":"dggoodwin","replyTo":"LIST","senderId":"y2P0QH8kTN_96KQaOVBfEW7cDk98htpnQdFwyUGUJXpXzyMCuHRaVQ4oLn2WLZOFa1rDuzTWf88l3eWGkBBoDpWQ8EZt2TeMVFDT","spamInfo":{"isSpam":false,"reason":"0"},"subject":"seminar","postDate":"1098445861","msgId":547,"canDelete":false,"contentTrasformed":false,"systemMessage":false,"headers":{"messageIdInHeader":"PEE1ODAzRjgwLTI0MjAtMTFEOS1BOTE1LTAwMEQ5M0FFMjQxQUBjYWx0ZWNoLmVkdT4="},"prevInTopic":0,"nextInTopic":0,"prevInTime":546,"nextInTime":548,"topicId":547,"numMessagesInTopic":1,"msgSnippet":"For those of you in the San Francisco Bay Area who are interested in such things, I will be giving a talk at Stanford next Wednesday Oct. 27 on","rawEmail":"Return-Path: &lt;dgoodwin@...&gt;\r\nX-Sender: dgoodwin@...\r\nX-Apparently-To: cantera@yahoogroups.com\r\nReceived: (qmail 79267 invoked from network); 22 Oct 2004 11:51:10 -0000\r\nReceived: from unknown (66.218.66.172)\n  by m20.grp.scd.yahoo.com with QMQP; 22 Oct 2004 11:51:10 -0000\r\nReceived: from unknown (HELO outgoing-mail.its.caltech.edu) (131.215.49.69)\n  by mta4.grp.scd.yahoo.com with SMTP; 22 Oct 2004 11:51:10 -0000\r\nReceived: from earth-dog (earth-dog [192.168.1.3])\n\tby water-ox-postvirus (Postfix) with ESMTP id DB89126AC67\n\tfor &lt;cantera@yahoogroups.com&gt;; Fri, 22 Oct 2004 04:51:08 -0700 (PDT)\r\nReceived: from earth-ox ([192.168.1.9])\n\tby earth-dog (MailMonitor for SMTP v1.2.2 ) ;\n\tFri, 22 Oct 2004 04:51:08 -0700 (PDT)\r\nReceived: from [10.0.1.3] (charter-241-056.caltech.edu [131.215.241.56])\n\tby earth-ox.its.caltech.edu (Postfix) with ESMTP id E7CF5109A8E\n\tfor &lt;cantera@yahoogroups.com&gt;; Fri, 22 Oct 2004 04:51:07 -0700 (PDT)\r\nMime-Version: 1.0 (Apple Message framework v619)\r\nContent-Transfer-Encoding: 7bit\r\nMessage-Id: &lt;A5803F80-2420-11D9-A915-000D93AE241A@...&gt;\r\nContent-Type: text/plain; charset=US-ASCII; format=flowed\r\nTo: cantera@yahoogroups.com\r\nDate: Fri, 22 Oct 2004 04:51:01 -0700\r\nX-Mailer: Apple Mail (2.619)\r\nX-Spam-Status: No, hits=0.0 tagged_above=-100000.0 required=5.0 \r\nX-Spam-Level: \r\nX-eGroups-Remote-IP: 131.215.49.69\r\nFrom: David Goodwin &lt;dgoodwin@...&gt;\r\nSubject: seminar\r\nX-Yahoo-Group-Post: member; u=44728387\r\nX-Yahoo-Profile: dggoodwin\r\n\r\nFor those of you in the San Francisco Bay Area who are interested in \nsuch things, I will be giving a talk at Stanford next Wednesday Oct. 27 \non &quot;Physically-Based Modeling of Solid-Oxide Fuel Cells,&quot;, including a \nlittle about Cantera&#39;s capabilities for multiphase heterogeneous \nchemistry / electrochemical simulations. This is part of their Fuel \nCell Seminar series, and will be held at 4:15 in room 127, building \n530.\n\n\n\n"}}