{"ygPerms":{"resourceCapabilityList":[{"resourceType":"GROUP","capabilities":[{"name":"READ"},{"name":"JOIN"}]},{"resourceType":"PHOTO","capabilities":[]},{"resourceType":"FILE","capabilities":[]},{"resourceType":"MEMBER","capabilities":[]},{"resourceType":"LINK","capabilities":[]},{"resourceType":"CALENDAR","capabilities":[]},{"resourceType":"DATABASE","capabilities":[]},{"resourceType":"POLL","capabilities":[]},{"resourceType":"MESSAGE","capabilities":[{"name":"READ"}]},{"resourceType":"PENDING_MESSAGE","capabilities":[]},{"resourceType":"ATTACHMENTS","capabilities":[{"name":"READ"}]},{"resourceType":"PHOTOMATIC_ALBUMS","capabilities":[]},{"resourceType":"MEMBERSHIP_TYPE","capabilities":[]},{"resourceType":"POST","capabilities":[{"name":"READ"}]},{"resourceType":"PIN","capabilities":[]}],"groupUrl":"groups.yahoo.com","intlCode":"us"},"comscore":"pageview_candidate","ygData":{"userId":44728387,"authorName":"David Goodwin","from":"David Goodwin &lt;dgoodwin@...&gt;","profile":"dggoodwin","replyTo":"LIST","senderId":"yTiL6rzuhPgwoO2DkSIo49MgFNHCw3HDstxc8jNA7BoTpsismKFGSoZVkOifsKck2t4V_9Ndav7-vs_2LMilg7oZzZg07o4b1ID_","spamInfo":{"isSpam":false,"reason":"0"},"subject":"Re: [cantera] 64 Bit SGI Build of Cantera","postDate":"1100300220","msgId":581,"canDelete":false,"contentTrasformed":false,"systemMessage":false,"headers":{"messageIdInHeader":"PDI5MkM2MUI2LTM0RkUtMTFEOS1CRURDLTAwMEQ5M0FFMjQxQUBjYWx0ZWNoLmVkdT4=","inReplyToHeader":"PDUuMS4xLjUuMi4yMDA0MTExMjEzMDUyMS4wMWJiNzY0MEBwb3BzZXJ2ZS5ncmMubmFzYS5nb3Y+","referencesHeader":"PDUuMS4xLjUuMi4yMDA0MTExMjEzMDUyMS4wMWJiNzY0MEBwb3BzZXJ2ZS5ncmMubmFzYS5nb3Y+"},"prevInTopic":579,"nextInTopic":0,"prevInTime":580,"nextInTime":582,"topicId":579,"numMessagesInTopic":2,"msgSnippet":"Maybe try the Python web site for tips, or Google. I think some work will be needed to get Cantera to run on 64-bit machines, but I am glad to see you are","rawEmail":"Return-Path: &lt;dgoodwin@...&gt;\r\nX-Sender: dgoodwin@...\r\nX-Apparently-To: cantera@yahoogroups.com\r\nReceived: (qmail 28921 invoked from network); 12 Nov 2004 22:57:03 -0000\r\nReceived: from unknown (66.218.66.166)\n  by m23.grp.scd.yahoo.com with QMQP; 12 Nov 2004 22:57:03 -0000\r\nReceived: from unknown (HELO outgoing-mail.its.caltech.edu) (131.215.49.69)\n  by mta5.grp.scd.yahoo.com with SMTP; 12 Nov 2004 22:57:03 -0000\r\nReceived: from water-dog (water-dog [192.168.1.26])\n\tby earth-ox-postvirus (Postfix) with ESMTP id 861D4109EB4\n\tfor &lt;cantera@yahoogroups.com&gt;; Fri, 12 Nov 2004 14:57:03 -0800 (PST)\r\nReceived: from water-ox ([192.168.1.10])\n\tby water-dog (MailMonitor for SMTP v1.2.2 ) ;\n\tFri, 12 Nov 2004 14:57:02 -0800 (PST)\r\nReceived: from [10.0.1.2] (charter-241-015.caltech.edu [131.215.241.15])\n\tby water-ox.its.caltech.edu (Postfix) with ESMTP id 992E126ACC7\n\tfor &lt;cantera@yahoogroups.com&gt;; Fri, 12 Nov 2004 14:57:02 -0800 (PST)\r\nMime-Version: 1.0 (Apple Message framework v619)\r\nIn-Reply-To: &lt;5.1.1.5.2.20041112130521.01bb7640@...&gt;\r\nReferences: &lt;5.1.1.5.2.20041112130521.01bb7640@...&gt;\r\nContent-Type: text/plain; charset=US-ASCII; delsp=yes; format=flowed\r\nMessage-Id: &lt;292C61B6-34FE-11D9-BEDC-000D93AE241A@...&gt;\r\nContent-Transfer-Encoding: 7bit\r\nDate: Fri, 12 Nov 2004 14:57:00 -0800\r\nTo: cantera@yahoogroups.com\r\nX-Mailer: Apple Mail (2.619)\r\nX-Spam-Status: No, hits=0.0 tagged_above=-100000.0 required=5.0 \r\nX-Spam-Level: \r\nX-eGroups-Remote-IP: 131.215.49.69\r\nFrom: David Goodwin &lt;dgoodwin@...&gt;\r\nSubject: Re: [cantera] 64 Bit SGI Build of Cantera\r\nX-Yahoo-Group-Post: member; u=44728387\r\nX-Yahoo-Profile: dggoodwin\r\n\r\nMaybe try the Python web site for tips, or Google.\n\nI think some work will be needed to get Cantera to run on 64-bit  \nmachines, but I am glad to see you are interested in doing it.  Please  \nlet me know if you get it to run!\n\nDave Goodwin\n\n\nOn Nov 12, 2004, at 10:08 AM, Anthony Iannetti wrote:\n\n&gt;\n&gt;\n&gt; Dear Cantera Users,\n&gt;\n&gt;\n&gt;          I am trying to build a 64 bit version of Cantera on my SGI.   \n&gt; Right\n&gt; now, I am stuck on trying to build a 64 bit version of Python.  Can  \n&gt; anybody\n&gt; send me the flags they use to build python on an SGI (using a 64 bit  \n&gt; build)?\n&gt;\n&gt; Thanks,\n&gt; Tony\n&gt;\n&gt; !---------------------------------------------------------------------- \n&gt; ---\n&gt; !  Anthony Iannetti\n&gt; !  Aerospace Engineer\n&gt; !  NASA Glenn Research Center\n&gt; !  Turbomachinery and Propulsion Division\n&gt; !  Combustion Branch\n&gt; !  phone:(216)433-5586\n&gt; !  fax:(216)433-5802\n&gt; !  email:\n&gt; Anthony.C.Iannetti@...\n&gt; !\n&gt; !  NOTE: NASA has changed my grc.nasa.gov email address to nasa.gov .\n&gt; ! \n&gt; _______________________________________________________________________ \n&gt; __\n&gt;\n&gt;\n&gt;\n&gt;\n&gt;\n&gt;\n&gt;\n&gt;\n&gt; Yahoo! Groups Links\n&gt;\n&gt;\n&gt;\n&gt;\n&gt;\n&gt;\n&gt;\n&gt;\n\n\n\n"}}