{"ygPerms":{"resourceCapabilityList":[{"resourceType":"GROUP","capabilities":[{"name":"READ"},{"name":"JOIN"}]},{"resourceType":"PHOTO","capabilities":[]},{"resourceType":"FILE","capabilities":[]},{"resourceType":"MEMBER","capabilities":[]},{"resourceType":"LINK","capabilities":[]},{"resourceType":"CALENDAR","capabilities":[]},{"resourceType":"DATABASE","capabilities":[]},{"resourceType":"POLL","capabilities":[]},{"resourceType":"MESSAGE","capabilities":[{"name":"READ"}]},{"resourceType":"PENDING_MESSAGE","capabilities":[]},{"resourceType":"ATTACHMENTS","capabilities":[{"name":"READ"}]},{"resourceType":"PHOTOMATIC_ALBUMS","capabilities":[]},{"resourceType":"MEMBERSHIP_TYPE","capabilities":[]},{"resourceType":"POST","capabilities":[{"name":"READ"}]},{"resourceType":"PIN","capabilities":[]}],"groupUrl":"groups.yahoo.com","intlCode":"us"},"comscore":"pageview_candidate","ygData":{"userId":122770107,"authorName":"usenechal","from":"&quot;usenechal&quot; &lt;senechal@...-dresden.de&gt;","profile":"usenechal","replyTo":"LIST","senderId":"uJoZ89W2Wktc2c0IqYusVdbAu87NqKq8dpW5UdMPf9Az4qkVs_K-G5gXYEdNRoCs5MPuB_MrtNx7ps_O0t9MlmgOjmcRDjQIjDUuTeG-Eyxuiw","spamInfo":{"isSpam":false,"reason":"0"},"subject":"Duplicate Reactions Error in 1.5.5","postDate":"1106232436","msgId":678,"canDelete":false,"contentTrasformed":false,"systemMessage":false,"headers":{"messageIdInHeader":"PGNzb2c5ays2cG4zQGVHcm91cHMuY29tPg=="},"prevInTopic":0,"nextInTopic":679,"prevInTime":677,"nextInTime":679,"topicId":678,"numMessagesInTopic":2,"msgSnippet":"Hi, when I try to load the konnov reaction mechanism(with python) I get an error: Procedure: installReaction Error:   Undeclared duplicate reactions detected: ","rawEmail":"Return-Path: &lt;senechal@...-dresden.de&gt;\r\nX-Sender: senechal@...-dresden.de\r\nX-Apparently-To: cantera@yahoogroups.com\r\nReceived: (qmail 74280 invoked from network); 20 Jan 2005 14:49:21 -0000\r\nReceived: from unknown (66.218.66.172)\n  by m24.grp.scd.yahoo.com with QMQP; 20 Jan 2005 14:49:21 -0000\r\nReceived: from unknown (HELO n9a.bulk.scd.yahoo.com) (66.94.237.43)\n  by mta4.grp.scd.yahoo.com with SMTP; 20 Jan 2005 14:49:21 -0000\r\nReceived: from [66.218.69.6] by n9.bulk.scd.yahoo.com with NNFMP; 20 Jan 2005 14:47:16 -0000\r\nReceived: from [66.218.66.87] by mailer6.bulk.scd.yahoo.com with NNFMP; 20 Jan 2005 14:47:16 -0000\r\nDate: Thu, 20 Jan 2005 14:47:16 -0000\r\nTo: cantera@yahoogroups.com\r\nMessage-ID: &lt;csog9k+6pn3@...&gt;\r\nUser-Agent: eGroups-EW/0.82\r\nMIME-Version: 1.0\r\nContent-Type: text/plain; charset=ISO-8859-1\r\nContent-Length: 728\r\nX-Mailer: Yahoo Groups Message Poster\r\nX-Yahoo-Newman-Property: groups-compose\r\nX-eGroups-Remote-IP: 66.94.237.43\r\nFrom: &quot;usenechal&quot; &lt;senechal@...-dresden.de&gt;\r\nSubject: Duplicate Reactions Error in 1.5.5\r\nX-Yahoo-Group-Post: member; u=122770107\r\nX-Yahoo-Profile: usenechal\r\n\r\n\nHi,\n\nwhen I try to load the konnov reaction mechanism(with python) I get an\nerror:\nProcedure: installReaction\nError:   Undeclared duplicate reactions detected: \nReaction 10: H + O2 (+ M) &lt;=&gt; HO2 (+ M)\nReaction 11: H + O2 (+ AR) &lt;=&gt; HO2 (+ AR)\n\nA look at the input file shows:\nH+O2(+M)=HO2(+M)               1.480E+12      0.6         0.0 \n    LOW /3.50E+16 -0.41 -1116.0/ \n    TROE /0.5 100000 10/\n AR/0.0/ H2O/10.6/ H2/1.5/ CO2/2.4/ \nH+O2(+AR)=HO2(+AR)             1.480E+12      0.6         0.0\n    LOW /7.00E+17 -0.8  0.0/\n    TROE /0.45 10 100000/ \n\nI earlier cantera-versions this mechanism worked, what do you suggest\n? Is now the &quot;duplicate&quot;-statement needed ? (The mechanism is\nconverted to .cti with ck2cti.exe.)\n\nulf\n\n\n\n\n\n"}}